quantsigns/__init__.py
quantsigns/metrics.py
quantsigns/quantsigns.py
QuantSigns-0.1.3.dist-info/METADATA
QuantSigns-0.1.3.dist-info/WHEEL
QuantSigns-0.1.3.dist-info/top_level.txt
QuantSigns-0.1.3.dist-info/RECORD
