Metadata-Version: 2.1
Name: QuantSigns
Version: 0.1.3
Summary: An API client for Quantsigns data
Author: QuantSigns
Author-email: support@quantsigns.com
Classifier: Development Status :: 3 - Alpha
Classifier: Intended Audience :: Developers
Classifier: License :: OSI Approved :: MIT License
Classifier: Programming Language :: Python :: 3
Classifier: Programming Language :: Python :: 3.8
Classifier: Programming Language :: Python :: 3.9
Classifier: Programming Language :: Python :: 3.10
Classifier: Operating System :: OS Independent
Requires-Python: >=3.6
Requires-Dist: requests
